phase_1_cli/__init__.py
phase_1_cli/main.py
phase_1_cli-0.1.0.dist-info/METADATA
phase_1_cli-0.1.0.dist-info/WHEEL
phase_1_cli-0.1.0.dist-info/entry_points.txt
phase_1_cli-0.1.0.dist-info/RECORD
