Metadata-Version: 2.4
Name: phase-1-cli
Version: 0.1.0
Summary: A beautiful, interactive terminal todo application with TUI and CLI interfaces
Project-URL: Homepage, https://github.com/marjan-ahmed/evolution-todo-sdd
Project-URL: Repository, https://github.com/marjan-ahmed/evolution-todo-sdd
Project-URL: Issues, https://github.com/marjan-ahmed/evolution-todo-sdd/issues
Author-email: Marjan Ahmed <marjan.ahmed08@yahoo.com>
License: MIT
Keywords: cli,productivity,task-manager,terminal,textual,todo,tui
Classifier: Development Status :: 4 - Beta
Classifier: Environment :: Console
Classifier: Intended Audience :: Developers
Classifier: Intended Audience :: End Users/Desktop
Classifier: License :: OSI Approved :: MIT License
Classifier: Operating System :: OS Independent
Classifier: Programming Language :: Python :: 3
Classifier: Programming Language :: Python :: 3.11
Classifier: Programming Language :: Python :: 3.12
Classifier: Topic :: Office/Business
Classifier: Topic :: Utilities
Classifier: Typing :: Typed
Requires-Python: >=3.11
Requires-Dist: pydantic>=2.12.5
Requires-Dist: pyfiglet>=1.0.2
Requires-Dist: rich>=14.2.0
Requires-Dist: textual>=6.11.0
Requires-Dist: typer>=0.15.1
